certified/__init__.py
certified/blob.py
certified/ca.py
certified/cert.py
certified/cert_base.py
certified/cert_info.py
certified/certified.py
certified/encode.py
certified/fast.py
certified/formatter.py
certified/layout.py
certified/loki.py
certified/message.py
certified/models.py
certified/ocsp.py
certified/py.typed
certified/serial.py
certified/test.py
certified/verify.py
certified/wrappers.py
certified-1.0.2.dist-info/LICENSE
certified-1.0.2.dist-info/METADATA
certified-1.0.2.dist-info/WHEEL
certified-1.0.2.dist-info/entry_points.txt
certified-1.0.2.dist-info/RECORD
