Metadata-Version: 2.3
Name: certified
Version: 1.0.2
Summary: The missing certificate infrastructure for web APIs.
License: BSD-3-Clause
Author: David M. Rogers
Author-email: predictivestatmech@gmail.com
Requires-Python: >=3.9,<4.0
Classifier: License :: OSI Approved :: BSD License
Classifier: Programming Language :: Python :: 3
Classifier: Programming Language :: Python :: 3.9
Classifier: Programming Language :: Python :: 3.10
Classifier: Programming Language :: Python :: 3.11
Classifier: Programming Language :: Python :: 3.12
Classifier: Programming Language :: Python :: 3.13
Provides-Extra: http
Requires-Dist: aiohttp (>=3.10.10,<4.0) ; extra == "http"
Requires-Dist: biscuit-python (>=0.3.0)
Requires-Dist: cryptography (>=43.0.1)
Requires-Dist: fastapi (>=0.115.0) ; extra == "http"
Requires-Dist: pydantic (>=2.8.2,<3.0)
Requires-Dist: python-logging-loki (>=0.3.1)
Requires-Dist: pyyaml (>=6.0.2,<7.0)
Requires-Dist: starlette (>=0.40.0) ; extra == "http"
Requires-Dist: typer (>=0.9)
Requires-Dist: uvicorn (>=0.30.6) ; extra == "http"
Project-URL: Documentation, https://certified.readthedocs.io/
Project-URL: Repository, https://github.com/ORNL/certified
